answer_engine_optimization/__init__.py
answer_engine_optimization/core.py
answer_engine_optimization-0.1.1.dist-info/LICENSE
answer_engine_optimization-0.1.1.dist-info/METADATA
answer_engine_optimization-0.1.1.dist-info/WHEEL
answer_engine_optimization-0.1.1.dist-info/top_level.txt
answer_engine_optimization-0.1.1.dist-info/RECORD
