Metadata-Version: 2.1
Name: answer-engine-optimization
Version: 0.1.1
Summary: Answer Engine Optimization (AEO) toolkit for Python-based websites
Home-page: https://supersharpai.com/answer-engine-optimization-toolkit
Author: SuperSharpAI.com
Author-email: python@supersharpai.com
License: UNKNOWN
Platform: UNKNOWN
Classifier: Programming Language :: Python :: 3
Classifier: License :: OSI Approved :: MIT License
Classifier: Operating System :: OS Independent
Classifier: Intended Audience :: Developers
Classifier: Topic :: Internet :: WWW/HTTP :: Site Management
Classifier: Topic :: Software Development :: Libraries :: Python Modules
Requires-Python: >=3.6
Requires-Dist: beautifulsoup4
